README.md
setup.py
dependencyinjection/__init__.py
dependencyinjection.egg-info/PKG-INFO
dependencyinjection.egg-info/SOURCES.txt
dependencyinjection.egg-info/dependency_links.txt
dependencyinjection.egg-info/not-zip-safe
dependencyinjection.egg-info/requires.txt
dependencyinjection.egg-info/top_level.txt
dependencyinjection/internal/__init__.py
dependencyinjection/internal/callsites.py
dependencyinjection/internal/checker.py
dependencyinjection/internal/common.py
dependencyinjection/internal/descriptors.py
dependencyinjection/internal/errors.py
dependencyinjection/internal/lock.py
dependencyinjection/internal/param_type_resolver.py
dependencyinjection/internal/provider.py
dependencyinjection/internal/scopedfactory.py
dependencyinjection/internal/services.py
dependencyinjection/internal/servicesmap.py