Metadata-Version: 1.0
Name: dependencyinjection
Version: 0.1.3.0
Summary: UNKNOWN
Home-page: https://github.com/Cologler/dependencyinjection-python
Author: cologler
Author-email: skyoflw@gmail.com
License: MIT
Keywords: python,dependencyinjection,di,ioc
Platform: UNKNOWN
